PuneetPackage.py
PuneetPackageTest.py
puneetpackagetest-0.0.1.dist-info/LICENSE
puneetpackagetest-0.0.1.dist-info/METADATA
puneetpackagetest-0.0.1.dist-info/WHEEL
puneetpackagetest-0.0.1.dist-info/top_level.txt
puneetpackagetest-0.0.1.dist-info/RECORD
